dialog_mariagpt/__init__.py
dialog_mariagpt/plugin.py
dialog_mariagpt-0.1.1.dist-info/METADATA
dialog_mariagpt-0.1.1.dist-info/WHEEL
dialog_mariagpt-0.1.1.dist-info/entry_points.txt
dialog_mariagpt-0.1.1.dist-info/RECORD
